koog_strategy_graph/__init__.py
koog_strategy_graph/base/__init__.py
koog_strategy_graph/base/http_chat_executor.py
koog_strategy_graph/base/http_utils.py
koog_strategy_graph/base/prompt_executor.py
koog_strategy_graph/base/provider_adapter.py
koog_strategy_graph/base/stream_text.py
koog_strategy_graph/core/__init__.py
koog_strategy_graph/core/agent.py
koog_strategy_graph/core/agent_dsl.py
koog_strategy_graph/core/checkpoint_sqlite.py
koog_strategy_graph/core/core.py
koog_strategy_graph/core/dsl.py
koog_strategy_graph/core/edge_extensions.py
koog_strategy_graph/core/environment.py
koog_strategy_graph/core/event_handler.py
koog_strategy_graph/core/events.py
koog_strategy_graph/core/features.py
koog_strategy_graph/core/history.py
koog_strategy_graph/core/llm_executor.py
koog_strategy_graph/core/mermaid.py
koog_strategy_graph/core/messages.py
koog_strategy_graph/core/option.py
koog_strategy_graph/core/persistence.py
koog_strategy_graph/core/response_processor.py
koog_strategy_graph/core/state_graph.py
koog_strategy_graph/core/streaming.py
koog_strategy_graph/core/structured.py
koog_strategy_graph/core/tool_selection.py
koog_strategy_graph/core/tools.py
koog_strategy_graph/core/a2a/__init__.py
koog_strategy_graph/core/a2a/client.py
koog_strategy_graph/core/a2a/server.py
koog_strategy_graph/core/a2a/types.py
koog_strategy_graph/core/acp/__init__.py
koog_strategy_graph/core/acp/client.py
koog_strategy_graph/core/acp/server.py
koog_strategy_graph/core/acp/types.py
koog_strategy_graph/core/built_in_tools/__init__.py
koog_strategy_graph/core/built_in_tools/echo.py
koog_strategy_graph/core/built_in_tools/time.py
koog_strategy_graph/core/observability/opentelemetry.py
koog_strategy_graph/core/tooling/__init__.py
koog_strategy_graph/core/tooling/class_tools.py
koog_strategy_graph/core/tooling/decorators.py
koog_strategy_graph/core/tooling/registry.py
koog_strategy_graph/core/tooling/schema.py
koog_strategy_graph/provider/anthropic_provider/anthropic_adapter.py
koog_strategy_graph-0.0.1.dist-info/licenses/LICENSE.txt
koog_strategy_graph-0.0.1.dist-info/licenses/NOTICE.txt
koog_strategy_graph-0.0.1.dist-info/METADATA
koog_strategy_graph-0.0.1.dist-info/WHEEL
koog_strategy_graph-0.0.1.dist-info/top_level.txt
koog_strategy_graph-0.0.1.dist-info/RECORD
