Metadata-Version: 2.4
Name: koog-strategy-graph
Version: 0.0.1
Summary: Koog-inspired strategy graph + agent runtime (stdlib-first).
Author: Dr. Roopam Kumar Gupta
License: 
Classifier: Programming Language :: Python :: 3
Classifier: Programming Language :: Python :: 3.11
Classifier: License :: OSI Approved :: Apache Software License
Classifier: Operating System :: OS Independent
Requires-Python: >=3.11
License-File: LICENSE.txt
License-File: NOTICE.txt
Provides-Extra: otel
Requires-Dist: opentelemetry-api>=1.0.0; extra == "otel"
Requires-Dist: opentelemetry-sdk>=1.0.0; extra == "otel"
Dynamic: license-file
